flopper/__init__.py
flopper/flopper.py
flopper/operations/__init__.py
flopper/operations/common.py
flopper/operations/elem_wise.py
flopper/operations/linalg.py
flopper/operations/zero_flops.py
flopper-0.2.2.dist-info/LICENSE
flopper-0.2.2.dist-info/METADATA
flopper-0.2.2.dist-info/WHEEL
flopper-0.2.2.dist-info/top_level.txt
flopper-0.2.2.dist-info/RECORD
