Metadata-Version: 2.1
Name: flopper
Version: 0.2.2
Summary: A Python to count flops of pytorch models.
Author-email: Andrea Boscolo Camiletto <abcamiletto@gmail.com>
Project-URL: Homepage, https://github.com/abcamiletto/flopper
Project-URL: Repository, https://github.com/abcamiletto/flopper
Requires-Python: >=3.8
License-File: LICENSE
Requires-Dist: fvcore>=0.1.5
Requires-Dist: torch>=1.8
Provides-Extra: dev
Requires-Dist: black; extra == "dev"
Requires-Dist: pre-commit; extra == "dev"
Requires-Dist: pytest; extra == "dev"
